pantos/common/__init__.py
pantos/common/blockchains/__init__.py
pantos/common/blockchains/avalanche.py
pantos/common/blockchains/base.py
pantos/common/blockchains/bnbchain.py
pantos/common/blockchains/celo.py
pantos/common/blockchains/contracts/__init__.py
pantos/common/blockchains/contracts/v0_2_0/__init__.py
pantos/common/blockchains/contracts/v0_2_0/avalanche_pantos_forwarder.abi
pantos/common/blockchains/contracts/v0_2_0/avalanche_pantos_hub.abi
pantos/common/blockchains/contracts/v0_2_0/avalanche_pantos_token.abi
pantos/common/blockchains/contracts/v0_2_0/avalanche_standard_token.abi
pantos/common/blockchains/contracts/v0_2_0/bnb_chain_pantos_forwarder.abi
pantos/common/blockchains/contracts/v0_2_0/bnb_chain_pantos_hub.abi
pantos/common/blockchains/contracts/v0_2_0/bnb_chain_pantos_token.abi
pantos/common/blockchains/contracts/v0_2_0/bnb_chain_standard_token.abi
pantos/common/blockchains/contracts/v0_2_0/celo_pantos_forwarder.abi
pantos/common/blockchains/contracts/v0_2_0/celo_pantos_hub.abi
pantos/common/blockchains/contracts/v0_2_0/celo_pantos_token.abi
pantos/common/blockchains/contracts/v0_2_0/celo_standard_token.abi
pantos/common/blockchains/contracts/v0_2_0/cronos_pantos_forwarder.abi
pantos/common/blockchains/contracts/v0_2_0/cronos_pantos_hub.abi
pantos/common/blockchains/contracts/v0_2_0/cronos_pantos_token.abi
pantos/common/blockchains/contracts/v0_2_0/cronos_standard_token.abi
pantos/common/blockchains/contracts/v0_2_0/ethereum_pantos_forwarder.abi
pantos/common/blockchains/contracts/v0_2_0/ethereum_pantos_hub.abi
pantos/common/blockchains/contracts/v0_2_0/ethereum_pantos_token.abi
pantos/common/blockchains/contracts/v0_2_0/ethereum_standard_token.abi
pantos/common/blockchains/contracts/v0_2_0/polygon_pantos_forwarder.abi
pantos/common/blockchains/contracts/v0_2_0/polygon_pantos_hub.abi
pantos/common/blockchains/contracts/v0_2_0/polygon_pantos_token.abi
pantos/common/blockchains/contracts/v0_2_0/polygon_standard_token.abi
pantos_common-6.0.1.dist-info/LICENSE.md
pantos_common-6.0.1.dist-info/WHEEL
pantos_common-6.0.1.dist-info/RECORD
pantos_common-6.0.1.dist-info/METADATA
